combinational_circuits/mux/mux.v
module mux (
    input a, b, c, d,
    input [1:0] s,
    output y
);

wire not_s0, not_s1;
wire and0, and1, and2, and3;

// Invert select bits
not U0(not_s0, s[0]);
not U1(not_s1, s[1]);

// AND gates to select inputs based on s
and U2(and0, a, not_s1, not_s0); // select 00
and U3(and1, b, not_s1, s[0]);   // select 01
and U4(and2, c, s[1], not_s0);   // select 10
and U5(and3, d, s[1], s[0]);     // select 11

// OR outputs to get final y
or U6(y, and0, and1, and2, and3);

endmodule

mux/mux_tb.v
module mux_tb;
reg a,b,c,d;
reg [1:0] s;
wire y;

mux dut (.a(a),.b(b),.c(c),.d(d),.s(s),.y(y));

initial
begin 
	{a,b,c,d}=4'b1010;
	s=2'b00; #5;
	s=2'b01; #5;
	s=2'b10; #5;
	s=2'b11; #5;

	{a,b,c,d}=4'b1111;
	s=2'b00; #5;
	s=2'b01; #5;
	s=2'b10; #5;
	s=2'b11; #5;

	{a,b,c,d}=4'b0000;
	s=2'b00; #5;
	s=2'b01; #5;
	s=2'b10; #5;
	s=2'b11; #5;

		{a,b,c,d}=4'b1001;
	s=2'b00; #5;
	s=2'b01; #5;
	s=2'b10; #5;
	s=2'b11; #5;
	$monitor("a=%b b=%b c=%b d=%b s=%b||y=%b",a,b,c,d,s,y);
	$finish;
end
initial
begin
	$dumpfile("mux.vcd");
	$dumpvars(0,mux_tb);
end
endmodule

combinational_circuits/mux/mux.vcd
$date
	Tue Sep 09 11:14:37 2025
$end
$version
	Icarus Verilog
$end
$timescale
	1s
$end
$scope module mux_tb $end
$var wire 1 ! y $end
$var reg 1 " a $end
$var reg 1 # b $end
$var reg 1 $ c $end
$var reg 1 % d $end
$var reg 2 & s [1:0] $end
$scope module dut $end
$var wire 1 " a $end
$var wire 1 ' and0 $end
$var wire 1 ( and1 $end
$var wire 1 ) and2 $end
$var wire 1 * and3 $end
$var wire 1 # b $end
$var wire 1 $ c $end
$var wire 1 % d $end
$var wire 1 + not_s0 $end
$var wire 1 , not_s1 $end
$var wire 2 - s [1:0] $end
$var wire 1 ! y $end
$upscope $end
$upscope $end
$enddefinitions $end
$comment Show the parameter values. $end
$dumpall
$end
#0
$dumpvars
b0 -
1,
1+
0*
0)
0(
1'
b0 &
0%
1$
0#
1"
1!
$end
#5
0!
0'
0+
b1 &
b1 -
#10
1!
1)
1+
0,
b10 &
b10 -
#15
0!
0)
0+
b11 &
b11 -
#20
1'
1+
1,
1!
0*
b0 &
b0 -
1#
1%
#25
0'
0+
1(
b1 &
b1 -
#30
1)
1!
1+
0,
0(
b10 &
b10 -
#35
0)
0+
1*
b11 &
b11 -
#40
1+
1,
0!
0*
b0 &
b0 -
0"
0#
0$
0%
#45
0+
b1 &
b1 -
#50
1+
0,
b10 &
b10 -
#55
0+
b11 &
b11 -
#60
1'
1+
1,
1!
0*
b0 &
b0 -
1"
1%
#65
0!
0'
0+
b1 &
b1 -
#70
1+
0,
b10 &
b10 -
#75
1!
0+
1*
b11 &
b11 -
