combinational_circuits/priority_encoder/prien.v
module prien (in,out,valid);
input  [3:0] in;   
output [1:0] out;   
output valid;
assign valid = |in; 

assign out = (in[3]) ? 2'b11 :
             (in[2]) ? 2'b10 :
             (in[1]) ? 2'b01 :
             (in[0]) ? 2'b00 :
            2'b00; 
endmodule

combinational_circuits/priority_encoder/prien_tb.v
module prien_tb;
reg [3:0] in;
wire [1:0] out;
wire valid;
prien uut (in,out,valid);
initial 
begin
    $monitor($time ," in=%b | out=%b valid=%b", in,out,valid);
    in=4'b0000; #10;
    in=4'b0001; #10;
    in=4'b0010; #10;
    in=4'b0011; #10;
    in=4'b0100; #10;
    in=4'b0101; #10;
    in=4'b0110; #10;
    in=4'b0111; #10;
    in=4'b1000; #10;
    in=4'b1111; #10;
    #100 $finish;
end
initial 
begin 
    $dumpfile("prien.vcd");
    $dumpvars(0,prien_tb);
end
endmodule

priority_encoder/prien.vcd
$date
	Tue Oct 07 20:40:43 2025
$end
$version
	Icarus Verilog
$end
$timescale
	1s
$end
$scope module prien_tb $end
$var wire 1 ! valid $end
$var wire 2 " out [1:0] $end
$var reg 4 # in [3:0] $end
$scope module uut $end
$var wire 4 $ in [3:0] $end
$var wire 1 ! valid $end
$var wire 2 % out [1:0] $end
$upscope $end
$upscope $end
$enddefinitions $end
$comment Show the parameter values. $end
$dumpall
$end
#0
$dumpvars
b0 %
b0 $
b0 #
b0 "
0!
$end
#10
1!
b1 #
b1 $
#20
b1 "
b1 %
b10 #
b10 $
#30
b11 #
b11 $
#40
b10 "
b10 %
b100 #
b100 $
#50
b101 #
b101 $
#60
b110 #
b110 $
#70
b111 #
b111 $
#80
b11 "
b11 %
b1000 #
b1000 $
#90
b1111 #
b1111 $
