combinational_circuits/fullsubtracter/fsub_s.v
module fsub_s(a,b,c,d,bo);
input a,b,c;
output d,bo;

    wire w1, w2, w3, w4;
    //diff
    xor(w1,a,b);
    xor(s,w1,c);
    //borrow
    or(w1,b,c);
    and(w2,b,c);
    not (w3,a);
    or(w4,w2,w3);
    and(bo,w1,w4);
endmodule

combinational_circuits/fullsubtracter/fsub_tb.v
`timescale 1ps/1ps
module fsub_tb;
reg a,b,c;
wire d,bo;

fsub_s dut (.a(a),.b(b),.c(c),.d(d),.bo(bo));
initial 
begin
a=0;b=0;c=0;

#10; a=0;b=0;c=1;
#10; a=0;b=1;c=0;
#10; a=0;b=1;c=1;
#10; a=1;b=0;c=0;
#10; a=1;b=0;c=1;
#10; a=1;b=1;c=0;
#10; a=1;b=1;c=1;
#10 $stop;
end

initial
begin
    $monitor("$time=%0t a=%b b=%b c=%b|| d=%b b0=%b", $time,a,b,c,d,bo);
end

initial begin
    $dumpfile("fsub_s.vcd");
    $dumpvars(0,fsub_tb);
end
endmodule

combinational_circuits/fullsubtracter/fsub_s.vcd
$date
	Tue Sep 09 11:05:03 2025
$end
$version
	Icarus Verilog
$end
$timescale
	1ps
$end
$scope module fsub_tb $end
$var wire 1 ! d $end
$var wire 1 " bo $end
$var reg 1 # a $end
$var reg 1 $ b $end
$var reg 1 % c $end
$scope module dut $end
$var wire 1 # a $end
$var wire 1 $ b $end
$var wire 1 " bo $end
$var wire 1 % c $end
$var wire 1 ! d $end
$var wire 1 & s $end
$var wire 1 ' w1 $end
$var wire 1 ( w2 $end
$var wire 1 ) w3 $end
$var wire 1 * w4 $end
$upscope $end
$upscope $end
$enddefinitions $end
$comment Show the parameter values. $end
$dumpall
$end
#0
$dumpvars
1*
1)
0(
0'
0&
0%
0$
0#
0"
z!
$end
#10
x"
x&
x'
1%
#20
1"
1&
1'
0%
1$
#30
0&
1(
1%
#40
0"
0*
x&
x'
0(
0)
0%
0$
1#
#50
0&
1'
1%
#60
x&
x'
0%
1$
#70
x"
1*
1(
1%
