combinational_circuits/encoders/encode.v
module encode (d0,d1,d2,d3,a1,a0);
input d0,d1,d2,d3;
output reg a1,a0;

always @(d0 or d1 or d2 or d3)
begin 
case ({d3,d2,d1,d0})
4'b0001: {a1,a0} = 2'b00;
4'b0010: {a1,a0} = 2'b01;
4'b0100: {a1,a0} = 2'b10;
4'b1000: {a1,a0} = 2'b11;
default : {a1,a0} = 2'bxx;
endcase
end endmodule

combinational_circuits/encoders/encode_tb.v
module encode_tb;
reg d0,d1,d2,d3;
wire a1,a0;
encode uut (.d0(d0),.d1(d1),.d2(d2),.d3(d3),.a1(a1),.a0(a0));
initial 
begin
    $monitor ($time, "d3=%b d2=%b d1=%b d0=%b || a1=%b a==%b", d3,d2,d1,d0,a0,a1);
    d3=0; d2=0; d1=0; d0=0;
    #10 d3=0; d2=0; d1=0; d0=1;
    #10 d3=0; d2=0; d1=1; d0=0;
    #10 d3=0; d2=1; d1=0; d0=0;
    #10 d3=1; d2=0; d1=0; d0=0;
    #10 $finish;
end
initial
begin
    $dumpfile ("encode.vcd");
    $dumpvars (0,encode_tb);
end
endmodule

combinational_circuits/encoders/encode.vcd
$date
	Tue Sep 09 10:45:27 2025
$end
$version
	Icarus Verilog
$end
$timescale
	1s
$end
$scope module encode_tb $end
$var wire 1 ! a1 $end
$var wire 1 " a0 $end
$var reg 1 # d0 $end
$var reg 1 $ d1 $end
$var reg 1 % d2 $end
$var reg 1 & d3 $end
$scope module uut $end
$var wire 1 # d0 $end
$var wire 1 $ d1 $end
$var wire 1 % d2 $end
$var wire 1 & d3 $end
$var reg 1 " a0 $end
$var reg 1 ! a1 $end
$upscope $end
$upscope $end
$enddefinitions $end
$comment Show the parameter values. $end
$dumpall
$end
#0
$dumpvars
0&
0%
0$
0#
x"
x!
$end
#10
0!
0"
1#
#20
1"
0#
1$
#30
1!
0"
0$
1%
#40
1"
0%
1&
#50
x!
x"
1$
1%
0&
#60
0$
1&
#70
1$
#80
1#
